[
  {
    "id": 0,
    "title": "Lasting Structures",
    "last_updated": "Jan 5, 2022",
    "content": "<ol><li>Solid foundations</li><li>Test, test, test</li><ol><li>Scientific method</li></ol><li>Use proven technologies and techniques</li><ol><li>Scientific method was applied</li></ol><li>Make it flexible</li><ol><li>examples: environment is apart of the design,&nbsp;</li><li>can stretch to new requirements</li><li>bridge</li></ol><li>Maintenance</li><ol><li>keep technical debt low</li></ol><li>Stay up to date</li><ol><li>Avoid your structure becoming obsolete, plan ahead</li><li>No need for your structure</li></ol></ol>"
  },
  {
    "id": 1,
    "title": "Continuous Improvement",
    "last_updated": "Jan 5, 2022",
    "content": "<ol><li>Solid foundations</li><li>Test, test, test</li><ol><li>Scientific method</li></ol><li>Use proven technologies and techniques</li><ol><li>Scientific method was applied</li></ol><li>Make it flexible</li><ol><li>examples: environment is apart of the design,&nbsp;</li><li>can stretch to new requirements</li><li>bridge</li></ol><li>Maintenance</li><ol><li>keep technical debt low</li></ol><li>Stay up to date</li><ol><li>Avoid your structure becoming obsolete, plan ahead</li><li>No need for your structure</li></ol></ol>"
  }
]